djangocms_file/__init__.py
djangocms_file/cms_plugins.py
djangocms_file/models.py
djangocms_file/locale/af/LC_MESSAGES/django.mo
djangocms_file/locale/af/LC_MESSAGES/django.po
djangocms_file/locale/ar/LC_MESSAGES/django.mo
djangocms_file/locale/ar/LC_MESSAGES/django.po
djangocms_file/locale/be/LC_MESSAGES/django.mo
djangocms_file/locale/be/LC_MESSAGES/django.po
djangocms_file/locale/bg/LC_MESSAGES/django.mo
djangocms_file/locale/bg/LC_MESSAGES/django.po
djangocms_file/locale/bn/LC_MESSAGES/django.mo
djangocms_file/locale/bn/LC_MESSAGES/django.po
djangocms_file/locale/ca/LC_MESSAGES/django.mo
djangocms_file/locale/ca/LC_MESSAGES/django.po
djangocms_file/locale/cmn/LC_MESSAGES/django.mo
djangocms_file/locale/cmn/LC_MESSAGES/django.po
djangocms_file/locale/cs/LC_MESSAGES/django.mo
djangocms_file/locale/cs/LC_MESSAGES/django.po
djangocms_file/locale/cy/LC_MESSAGES/django.mo
djangocms_file/locale/cy/LC_MESSAGES/django.po
djangocms_file/locale/da/LC_MESSAGES/django.mo
djangocms_file/locale/da/LC_MESSAGES/django.po
djangocms_file/locale/de/LC_MESSAGES/django.mo
djangocms_file/locale/de/LC_MESSAGES/django.po
djangocms_file/locale/el/LC_MESSAGES/django.mo
djangocms_file/locale/el/LC_MESSAGES/django.po
djangocms_file/locale/en/LC_MESSAGES/django.mo
djangocms_file/locale/en/LC_MESSAGES/django.po
djangocms_file/locale/es/LC_MESSAGES/django.mo
djangocms_file/locale/es/LC_MESSAGES/django.po
djangocms_file/locale/es_AR/LC_MESSAGES/django.mo
djangocms_file/locale/es_AR/LC_MESSAGES/django.po
djangocms_file/locale/es_BO/LC_MESSAGES/django.mo
djangocms_file/locale/es_BO/LC_MESSAGES/django.po
djangocms_file/locale/es_DO/LC_MESSAGES/django.mo
djangocms_file/locale/es_DO/LC_MESSAGES/django.po
djangocms_file/locale/et/LC_MESSAGES/django.mo
djangocms_file/locale/et/LC_MESSAGES/django.po
djangocms_file/locale/eu/LC_MESSAGES/django.mo
djangocms_file/locale/eu/LC_MESSAGES/django.po
djangocms_file/locale/fa/LC_MESSAGES/django.mo
djangocms_file/locale/fa/LC_MESSAGES/django.po
djangocms_file-3.0.1.dist-info/LICENSE
djangocms_file-3.0.1.dist-info/METADATA
djangocms_file-3.0.1.dist-info/WHEEL
djangocms_file-3.0.1.dist-info/top_level.txt
djangocms_file-3.0.1.dist-info/RECORD
